aaaaa_dict_unpacking_at_home.pth
dict_unpacking_at_home.py
dict_unpacking_at_home-1.0.0.dist-info/METADATA
dict_unpacking_at_home-1.0.0.dist-info/WHEEL
dict_unpacking_at_home-1.0.0.dist-info/entry_points.txt
dict_unpacking_at_home-1.0.0.dist-info/top_level.txt
dict_unpacking_at_home-1.0.0.dist-info/RECORD
