Metadata-Version: 2.1
Name: dict_unpacking_at_home
Version: 1.0.0
Summary: can we have dict unpacking in python?
Home-page: https://github.com/asottile/dict-unpacking-at-home
Author: Anthony Sottile
Author-email: asottile@umich.edu
License: MIT
Classifier: License :: OSI Approved :: MIT License
Classifier: Programming Language :: Python :: 3
Classifier: Programming Language :: Python :: 3 :: Only
Classifier: Programming Language :: Python :: Implementation :: CPython
Requires-Python: >=3.10
Requires-Dist: tokenize-rt>=6.1
